feii/__init__.py
feii/alias.py
feii/aliases.py
feii/cli.py
feii/close.py
feii/cluster.py
feii/config.py
feii/delete.py
feii/error.py
feii/function.py
feii/ilm.py
feii/index.py
feii/init.py
feii/log.py
feii/main.py
feii/mapping.py
feii/path_to_file.py
feii/policy.py
feii/request.py
feii/rollover.py
feii/shard.py
feii/structure.py
feii/update.py
feii/write.py
feii/commands/__init__.py
feii/commands/cmd_alias.py
feii/commands/cmd_close.py
feii/commands/cmd_delete.py
feii/commands/cmd_error.py
feii/commands/cmd_policy.py
feii/commands/cmd_rollover.py
feii/commands/cmd_update.py
feii/commands/cmd_write.py
feii/commands/alias/__init__.py
feii/commands/alias/cmd_empty.py
feii/commands/alias/cmd_primary.py
feii/commands/alias/cmd_second.py
feii/commands/close/__init__.py
feii/commands/close/cmd_old-policy.py
feii/commands/delete/__init__.py
feii/commands/delete/cmd_last.py
feii/commands/delete/cmd_not-last.py
feii/commands/delete/cmd_old-policy.py
feii/commands/error/__init__.py
feii/commands/error/cmd_ilm.py
feii/commands/error/cmd_mapping.py
feii/commands/error/cmd_retry.py
feii/commands/policy/__init__.py
feii/commands/policy/cmd_update.py
feii/commands/rollover/__init__.py
feii/commands/rollover/cmd_last-index.py
feii/commands/rollover/cmd_last-shrink-index.py
feii/commands/rollover/cmd_next-warm-step.py
feii/commands/rollover/cmd_not-last-index.py
feii/commands/update/__init__.py
feii/commands/update/cmd_timeout.py
feii/commands/write/__init__.py
feii/commands/write/cmd_closed.py
feii/commands/write/cmd_primary.py
feii-0.9.9.dist-info/METADATA
feii-0.9.9.dist-info/WHEEL
feii-0.9.9.dist-info/entry_points.txt
feii-0.9.9.dist-info/top_level.txt
feii-0.9.9.dist-info/RECORD
