Metadata-Version: 2.1
Name: feii
Version: 0.9.9
Summary: Fix error ilm index in Elasticsearch
Home-page: https://github.com/antohhh93/feii
Author: Anton Turko
Author-email: anton_turko@mail.ru
License: MIT
Platform: UNKNOWN
Classifier: Programming Language :: Python :: Implementation
Classifier: Programming Language :: Python :: 3
Classifier: Natural Language :: English
Classifier: License :: OSI Approved :: MIT License
Requires-Dist: requests (>=2)
Requires-Dist: click
